pysiology/__init__.py
pysiology/electrocardiography.py
pysiology/electrodermalactivity.py
pysiology/electromyography.py
pysiology/sampledata.py
pysiology-0.0.9.6.dist-info/LICENSE
pysiology-0.0.9.6.dist-info/METADATA
pysiology-0.0.9.6.dist-info/WHEEL
pysiology-0.0.9.6.dist-info/top_level.txt
pysiology-0.0.9.6.dist-info/RECORD
