Metadata-Version: 2.1
Name: pysiology
Version: 0.0.9.6
Summary: Physiological signal processing in Python
Home-page: https://github.com/Gabrock94/Pysiology
Download-URL: https://github.com/Gabrock94/Pysiology/archive/0.9.5.tar.gz
Author: Giulio Gabrieli
Author-email: gack94@gmail.com
License: GPL-3.0
Keywords: ECG,EMG,EDA,GSR,Physiology,Signal Processing
Platform: UNKNOWN
Classifier: Development Status :: 4 - Beta
Classifier: License :: OSI Approved :: GNU General Public License (GPL)
Classifier: Programming Language :: Python :: 2
Classifier: Programming Language :: Python :: 2.6
Classifier: Programming Language :: Python :: 2.7
Classifier: Programming Language :: Python :: 3
Classifier: Programming Language :: Python :: 3.2
Classifier: Programming Language :: Python :: 3.3
Classifier: Programming Language :: Python :: 3.4
Classifier: Operating System :: MacOS :: MacOS X
Classifier: Operating System :: Microsoft :: Windows
Classifier: Operating System :: POSIX :: Linux
Classifier: Topic :: Scientific/Engineering
Classifier: Topic :: Scientific/Engineering :: Medical Science Apps.
Classifier: Intended Audience :: Science/Research
Classifier: Intended Audience :: Healthcare Industry
Classifier: Intended Audience :: Education
License-File: LICENSE
Requires-Dist: numpy
Requires-Dist: peakutils
Requires-Dist: scipy
Requires-Dist: matplotlib
